rodina_forum_api_async-1.0.0.dist-info/licenses/LICENSE
rodina_forum_async/__init__.py
rodina_forum_async/api.py
rodina_forum_async/consts.py
rodina_forum_async/exceptions.py
rodina_forum_async/bypass_antibot/__init__.py
rodina_forum_async/bypass_antibot/script.py
rodina_forum_async/models/__init__.py
rodina_forum_async/models/category_object.py
rodina_forum_async/models/member_object.py
rodina_forum_async/models/other.py
rodina_forum_async/models/post_object.py
rodina_forum_async/models/thread_object.py
rodina_forum_api_async-1.0.0.dist-info/METADATA
rodina_forum_api_async-1.0.0.dist-info/WHEEL
rodina_forum_api_async-1.0.0.dist-info/top_level.txt
rodina_forum_api_async-1.0.0.dist-info/RECORD
