Metadata-Version: 2.4
Name: rodina-forum-api-async
Version: 1.0.0
Summary: Асинхронная Python библиотека для взаимодействия с форумом Rodina RP (forum.rodina-rp.com) без необходимости получения API ключа.
Home-page: https://github.com/fakelag28/Rodina-Forum-API-Async
Author: fakelag28
Author-email: fakelag712@gmail.com
Classifier: Programming Language :: Python :: 3
Classifier: License :: OSI Approved :: MIT License
Classifier: Operating System :: OS Independent
Requires-Python: >=3.6
License-File: LICENSE
Requires-Dist: aiohttp
Requires-Dist: aiohttp-socks
Requires-Dist: beautifulsoup4
Requires-Dist: dukpy
Requires-Dist: lxml
Dynamic: author
Dynamic: author-email
Dynamic: classifier
Dynamic: description
Dynamic: description-content-type
Dynamic: home-page
Dynamic: license-file
Dynamic: requires-dist
Dynamic: requires-python
Dynamic: summary
